<Dealers>	///ROOT ELEMENT			                                 ///annotate all layers of the xml
	<Dealer id="485"> ///TAGS
		<Name>Wacky Bob’s Automall</Name> 
		<Vehicle type="suv" id="848432">
			<Price unit="pounds">17000</Price> ///ATTRIBUTES      ///These are called attributes i.e. "unit = 'pounds'" and type = "suv"
			<Make>Land Rover</Make>
			<Model>Range Rover</Model>
		</Vehicle>
		<Vehicle type="pickup" id="52523">
			<Price unit="dollars">22600</Price>
			<Make>Toyota</Make>
			<Model>Tundra</Model>
		</Vehicle>
		<Vehicle type="sedan" id="151e5dde">
			<Price unit="dollars">36600</Price>
			<Make>Genesis</Make>
			<Model>G70</Model>
		</Vehicle>
		<Vehicle type="sports car" id="ern222">
			<Price unit="dollars">22330</Price>
			<Make>Mazda</Make>
			<Model>Miata</Model>
		</Vehicle>
	</Dealer>
</Dealers>
